sphinx_prolog/__init__.py
sphinx_prolog/infobox.py
sphinx_prolog/pprolog.py
sphinx_prolog/solex.py
sphinx_prolog/swish.py
sphinx_prolog/_static/jquery-ui.min.css
sphinx_prolog/_static/jquery-ui.min.js
sphinx_prolog/_static/jquery.js
sphinx_prolog/_static/lpn.css
sphinx_prolog/_static/lpn.js
sphinx_prolog/_static/sphinx-prolog.css
sphinx_prolog/_static/lpn/lpn-close.png
sphinx_prolog/_static/lpn/lpn-run.png
sphinx_prolog-0.6.dist-info/LICENCE
sphinx_prolog-0.6.dist-info/METADATA
sphinx_prolog-0.6.dist-info/WHEEL
sphinx_prolog-0.6.dist-info/top_level.txt
sphinx_prolog-0.6.dist-info/RECORD
