Metadata-Version: 2.1
Name: sphinx-prolog
Version: 0.6
Summary: A collection of Sphinx (and Jupyter Book) extensions for authoring interactive SWI Prolog code blocks.
Home-page: https://github.com/simply-logical/sphinx-prolog
Maintainer: Kacper Sokol
Maintainer-email: k.sokol@bristol.ac.uk
License: new BSD
Download-URL: https://pypi.org/project/sphinx-prolog/#files
Platform: UNKNOWN
Requires-Python: ~=3.9
License-File: LICENCE
Requires-Dist: docutils
Requires-Dist: pygments
Requires-Dist: sphinx>=5
